freenit/bin/build.sh
freenit/bin/common.sh
freenit/bin/devel.sh
freenit/bin/freenit.sh
freenit/bin/init.sh
freenit/bin/publish.sh
freenit/bin/security.sh
freenit/bin/shell.sh
freenit/bin/test.sh
freenit/__init__.py
freenit/app.py
freenit/auth.py
freenit/base_config.py
freenit/cli.py
freenit/config.py
freenit/decorators.py
freenit/mail.py
freenit/migration.py
freenit/permissions.py
freenit/api/__init__.py
freenit/api/router.py
freenit/api/theme.py
freenit/api/auth/__init__.py
freenit/api/domain/__init__.py
freenit/api/domain/ldap.py
freenit/api/role/__init__.py
freenit/api/role/ldap.py
freenit/api/role/sql.py
freenit/api/user/__init__.py
freenit/api/user/ldap.py
freenit/api/user/sql.py
freenit/models/__init__.py
freenit/models/pagination.py
freenit/models/role.py
freenit/models/safe.py
freenit/models/theme.py
freenit/models/user.py
freenit/models/ldap/__init__.py
freenit/models/ldap/base.py
freenit/models/ldap/domain.py
freenit/models/ldap/group.py
freenit/models/ldap/role.py
freenit/models/ldap/user.py
freenit/models/sql/__init__.py
freenit/models/sql/base.py
freenit/models/sql/role.py
freenit/models/sql/theme.py
freenit/models/sql/user.py
freenit/project/.gitignore
freenit/project/LICENSE
freenit/project/alembic.ini
freenit/project/main.py
freenit/project/migrate.py
freenit/project/provisioners.mk
freenit/project/pyproject.toml
freenit/project/requirements.yml
freenit/project/alembic/script.py.mako
freenit/project/ansible/group_vars/.keep
freenit/project/ansible/inventory/.keep
freenit/project/ansible/roles/devel/tasks/main.yml
freenit/project/ansible/roles/devel/vars/main.yml
freenit/project/bin/build.sh
freenit/project/bin/common.sh
freenit/project/bin/devel.sh
freenit/project/bin/init.sh
freenit/project/bin/shell.sh
freenit/project/bin/test.sh
freenit/project/project/__init__.py
freenit/project/project/app.py
freenit/project/project/base_config.py
freenit/project/project/config.py
freenit/project/project/api/__init__.py
freenit-0.3.22.dist-info/METADATA
freenit-0.3.22.dist-info/WHEEL
freenit-0.3.22.dist-info/entry_points.txt
freenit-0.3.22.dist-info/licenses/LICENSE
freenit-0.3.22.dist-info/RECORD
