Metadata-Version: 2.4
Name: freenit
Version: 0.3.22
Summary: REST API framework based on FastAPI
Project-URL: Homepage, https://freenit.org
Project-URL: Repository, https://github.com/freenit-framework/backend
Author-email: Goran Mekić <meka@tilda.center>
License: BSD 2-Clause License
License-File: LICENSE
Classifier: Development Status :: 4 - Beta
Classifier: Environment :: Web Environment
Classifier: Intended Audience :: Developers
Classifier: Programming Language :: Python
Classifier: Topic :: Internet :: WWW/HTTP
Requires-Python: >=3.8
Requires-Dist: fastapi
Requires-Dist: passlib
Requires-Dist: prompt-toolkit
Requires-Dist: pydantic[email]
Requires-Dist: pyjwt
Provides-Extra: all
Requires-Dist: aiosqlite; extra == 'all'
Requires-Dist: alembic; extra == 'all'
Requires-Dist: bandit; extra == 'all'
Requires-Dist: beanie; extra == 'all'
Requires-Dist: bonsai; extra == 'all'
Requires-Dist: httpx; extra == 'all'
Requires-Dist: mkdocs; extra == 'all'
Requires-Dist: mkdocs-awesome-pages-plugin; extra == 'all'
Requires-Dist: mkdocs-material; extra == 'all'
Requires-Dist: ormar; extra == 'all'
Requires-Dist: pytest-asyncio; extra == 'all'
Requires-Dist: pytest-factoryboy; extra == 'all'
Requires-Dist: requests; extra == 'all'
Requires-Dist: ruff; extra == 'all'
Requires-Dist: twine; extra == 'all'
Requires-Dist: uvicorn; extra == 'all'
Provides-Extra: build
Requires-Dist: twine; extra == 'build'
Provides-Extra: dev
Requires-Dist: aiosqlite; extra == 'dev'
Requires-Dist: ruff; extra == 'dev'
Requires-Dist: uvicorn; extra == 'dev'
Provides-Extra: doc
Requires-Dist: mkdocs; extra == 'doc'
Requires-Dist: mkdocs-awesome-pages-plugin; extra == 'doc'
Requires-Dist: mkdocs-material; extra == 'doc'
Provides-Extra: ldap
Requires-Dist: bonsai; extra == 'ldap'
Provides-Extra: mongo
Requires-Dist: beanie; extra == 'mongo'
Provides-Extra: sql
Requires-Dist: alembic; extra == 'sql'
Requires-Dist: ormar; extra == 'sql'
Provides-Extra: test
Requires-Dist: aiosqlite; extra == 'test'
Requires-Dist: bandit; extra == 'test'
Requires-Dist: httpx; extra == 'test'
Requires-Dist: pytest-asyncio; extra == 'test'
Requires-Dist: pytest-factoryboy; extra == 'test'
Requires-Dist: requests; extra == 'test'
Requires-Dist: ruff; extra == 'test'
